smooth_operator_agent_tools/__init__.py
smooth_operator_agent_tools/api_classes.py
smooth_operator_agent_tools/installedversion.txt
smooth_operator_agent_tools/server_utils.py
smooth_operator_agent_tools/smooth-operator-server.zip
smooth_operator_agent_tools/smooth_operator_client.py
smooth_operator_agent_tools/models/__init__.py
smooth_operator_agent_tools/models/models.py
smooth_operator_agent_tools/server/__init__.py
smooth_operator_agent_tools/server/installedversion.txt
smooth_operator_agent_tools/server/smooth-operator-server.zip
smooth_operator_agent_tools-1.0.112.dist-info/licenses/LICENSE
smooth_operator_agent_tools-1.0.112.dist-info/METADATA
smooth_operator_agent_tools-1.0.112.dist-info/WHEEL
smooth_operator_agent_tools-1.0.112.dist-info/top_level.txt
smooth_operator_agent_tools-1.0.112.dist-info/RECORD
