Metadata-Version: 2.4
Name: smooth-operator-agent-tools
Version: 1.0.112
Summary: Python client library for the Smooth Operator agent tools API.
Author-email: Smooth Operator <florian.standhartinger@gmail.com>
License-Expression: MIT
Project-URL: Homepage, https://github.com/fstandhartinger/smooth-operator-client-python
Project-URL: Bug Tracker, https://github.com/fstandhartinger/smooth-operator-client-python/issues
Classifier: Programming Language :: Python :: 3
Classifier: Operating System :: OS Independent
Classifier: Intended Audience :: Developers
Classifier: Topic :: Software Development :: Libraries :: Python Modules
Requires-Python: >=3.8
License-File: LICENSE
Requires-Dist: requests>=2.20.0
Dynamic: license-file
